snl_regression_quality/__init__.py
snl_regression_quality/load_data.py
snl_regression_quality/snl_regression.py
snl_regression_quality/test_time.py
snl_regression_quality/data/data_X.csv
snl_regression_quality/data/data_Y.csv
snl_regression_quality/data/test_X.csv
snl_regression_quality/data/test_Y.csv
snl_regression_quality/modules/__init__.py
snl_regression_quality/modules/methods/__init__.py
snl_regression_quality/modules/methods/reading_data.py
snl_regression_quality/modules/methods/remove_outlier.py
snl_regression_quality/modules/methods/scaling_data.py
snl_regression_quality/modules/methods/user_messages_initial.py
snl_regression_quality/modules/methods/waveform_regression.py
snl_regression_quality/modules/metrics/__init__.py
snl_regression_quality/modules/metrics/calculate_assumptions.py
snl_regression_quality/modules/metrics/calculate_quality.py
snl_regression_quality/modules/utils/__init__.py
snl_regression_quality/modules/utils/global_constants.py
snl_regression_quality/modules/utils/ram_consumption.py
snl_exp_regression_quality-0.2.0.dist-info/METADATA
snl_exp_regression_quality-0.2.0.dist-info/WHEEL
snl_exp_regression_quality-0.2.0.dist-info/top_level.txt
snl_exp_regression_quality-0.2.0.dist-info/RECORD
