Metadata-Version: 2.4
Name: snl_exp_regression_quality
Version: 0.2.0
Summary: simple no linear regression quality (Exponential)
Home-page: https://github.com/aplatag/project_SNL_regression_quality
Author: EdelH, Aplatag
License: MIT
Requires-Dist: numpy
Requires-Dist: pandas
Requires-Dist: scikit-rf
Requires-Dist: matplotlib
Requires-Dist: scipy
Requires-Dist: scikit-learn
Requires-Dist: art
Requires-Dist: tqdm
Dynamic: author
Dynamic: description
Dynamic: description-content-type
Dynamic: home-page
Dynamic: license
Dynamic: requires-dist
Dynamic: summary
